scp_constructor/__init__.py
scp_constructor/cli.py
scp_constructor/export.py
scp_constructor/graph.py
scp_constructor/neo4j_sync.py
scp_constructor/scanner/__init__.py
scp_constructor/scanner/github.py
scp_constructor/scanner/local.py
scp_constructor-0.4.3.dist-info/METADATA
scp_constructor-0.4.3.dist-info/WHEEL
scp_constructor-0.4.3.dist-info/entry_points.txt
scp_constructor-0.4.3.dist-info/RECORD
