Metadata-Version: 2.4
Name: scp-constructor
Version: 0.4.3
Summary: Build architecture models from scp.yaml files
Project-URL: Homepage, https://systemcapabilityprotocol.com/
Project-URL: Documentation, https://systemcapabilityprotocol.com/integrations
Project-URL: Repository, https://github.com/krackenservices/scp-integrations.git
Project-URL: Issues, https://github.com/krackenservices/scp-integrations/issues
Author-email: Kracken Services <scp@krackenservices.com>
License: MIT
Keywords: architecture,cli,dependency-graph,neo4j,scp
Classifier: Development Status :: 4 - Beta
Classifier: Environment :: Console
Classifier: Intended Audience :: Developers
Classifier: License :: OSI Approved :: MIT License
Classifier: Operating System :: OS Independent
Classifier: Programming Language :: Python :: 3
Classifier: Programming Language :: Python :: 3.12
Classifier: Programming Language :: Python :: 3.13
Classifier: Topic :: Software Development :: Libraries :: Python Modules
Classifier: Typing :: Typed
Requires-Python: >=3.12
Requires-Dist: httpx>=0.25
Requires-Dist: neo4j>=5.0
Requires-Dist: rich>=13.0
Requires-Dist: scp-sdk>=0.2.0
Requires-Dist: typer>=0.9
